survive/__init__.py
survive/survival_data.py
survive/base/__init__.py
survive/base/model.py
survive/datasets/__init__.py
survive/datasets/load.py
survive/datasets/data/channing.csv
survive/datasets/data/leukemia.csv
survive/nonparametric/__init__.py
survive/nonparametric/base.py
survive/nonparametric/kaplan_meier.py
survive/nonparametric/nelson_aalen.py
survive/utils/__init__.py
survive/utils/plotting.py
survive/utils/validation.py
survive-0.3.dist-info/METADATA
survive-0.3.dist-info/RECORD
survive-0.3.dist-info/WHEEL
survive-0.3.dist-info/top_level.txt
