Metadata-Version: 2.1
Name: survive
Version: 0.3
Summary: Survival analysis in Python
Home-page: https://github.com/artemmavrin/survive
Author: Artem Mavrin
Author-email: amavrin@ucsd.edu
License: UNKNOWN
Platform: UNKNOWN
Classifier: Programming Language :: Python :: 3
Classifier: Programming Language :: Python :: 3.6
Classifier: Programming Language :: Python :: 3.7
Classifier: License :: OSI Approved :: MIT License
Classifier: Operating System :: OS Independent
Provides-Extra: seaborn
Requires-Dist: numpy
Requires-Dist: scipy
Requires-Dist: pandas
Requires-Dist: matplotlib
Provides-Extra: seaborn
Requires-Dist: seaborn; extra == 'seaborn'
